{"uid":2634,"premise":"الرئيس الجزائري يقيل رئيس جهاز الأمن الوطني عبد الغني هامل","hypothesis":"اقالة رئيس جهاز الأمن الوطني الجزائري عبد الغني هامل","label":"agree"}
{"uid":994,"premise":"تريليون دولاتر أس مال شركة","hypothesis":"شركة تصل لرأس مال يقدر بـ مليون دولار","label":"disagree"}
{"uid":2598,"premise":"لبنان ترمي الدبابات في عرض البحر!","hypothesis":"إسرائيل ترمي الدبابات في البحر!","label":"disagree"}
{"uid":1448,"premise":"البريطانية آنا بيرنز تفوز بجائزة مان بوكر المرموقة عن روايتها بائع الحليب","hypothesis":"جائزة مان بوكر المرموقة من نصيب البريطانية آنا بيرنز عن روايتها بائع الحليب","label":"agree"}
{"uid":1151,"premise":"النفط يهبط مع تزايد الإمدادات والتوترات التجارية","hypothesis":"ارتفاع أسعار النفط رغم زيادة الإمدادات","label":"disagree"}
{"uid":1319,"premise":"محاكمة مواطن فرنسي في القدس بتهمة تهريب أسلحة من غزة","hypothesis":"مواطن فرنسي يواجه المحاكمة في القدس لتهريبه أسلحة من غزة","label":"agree"}
{"uid":1542,"premise":"الذهب والدولار تناسب طردي","hypothesis":"انخفاض الدولار يرفع الذهب","label":"disagree"}
{"uid":1267,"premise":"الاتحاد الأوروبي:  ترامب يصوب مسدسا إلى رأسنا","hypothesis":"الاتحاد الأوروبي يصف ترامب بأنه يصوب سلاحه إليهم","label":"agree"}
{"uid":1036,"premise":"طالبت تركيا أمريكا بألا تسمح للأكراد بإرسال الدعم إلى عفرين","hypothesis":"تركيا تنادي بإرسال الدعم إلى عفرين","label":"disagree"}
{"uid":254,"premise":"الإمدادات والتوترات تؤديان لانخفاض أسعار النفط","hypothesis":"ارتفاع أسعار النفط رغم زيادة الإمدادات","label":"disagree"}
{"uid":1256,"premise":"المتحدث باسم رئيس الوزراء الإسرائيلي يؤكد نقل نتنياهو للمستشفى","hypothesis":"نتنياهو يُنققل للمستشفى و المتحدث باسمه يؤكد ذلك","label":"agree"}
{"uid":883,"premise":"اعترضت قوات الدفاعات السعودية صاروخا باليستيا فوق الرياض","hypothesis":"قوات الدفاعات السعودية تفشل فى التصدي لصاروخ باليستيا فوق الرياض","label":"disagree"}
{"uid":2500,"premise":"المفوضية الأوروبية تعلن الحرب على المنتجات البلاستيكية","hypothesis":"منتجات البلاستيك تغزو السوق الأوروبية","label":"disagree"}
{"uid":842,"premise":"أوسكار 2018: ما المتوقع خلال حفل توزيع الجوائز هذا العام","hypothesis":"أوسكار 2010: ما المتوقع خلال حفل توزيع الجوائز هذا العام","label":"disagree"}
{"uid":25,"premise":"الذهب يتراجع مع تصريحات ترامب حول كوريا الشمالية","hypothesis":"الذهب يرتفع مع تصريحات ترامب حول كوريا الشمالية","label":"disagree"}
{"uid":852,"premise":"الدفاع الجوي السوري يتصدى لهجوم صاروخي على قاعدة جوية في حمص","hypothesis":"فشل الدفاع الجوي السوري فى التصدى لهجوم على قاعدة جوية في حمص","label":"disagree"}
{"uid":1982,"premise":"الدولار يحلّق واليورو يهبط بسبب الليرة التركية","hypothesis":"زيادة في سعر اليورو و انخفاض لسعر الدولار بسبب الليرة التركية","label":"disagree"}
{"uid":1055,"premise":"خاشقجي في مقاله الأخير: العالم العربي يحتاج إلى حرية الصحافة","hypothesis":"كتب خاشقجي في مقاله الأخير أن العالم العربي ينعم بحرية الصحافة","label":"disagree"}
{"uid":2479,"premise":"تقارير عن اعتقال رجل الدين المحافظ ناصر العمر في السعودية","hypothesis":"تم إلقاء القبض على ناصر العمر في سوريا","label":"disagree"}
{"uid":518,"premise":"المحكمة الدستورية في مصر لا تعترف بأحكام القضاء بشأن تيران وصنافير","hypothesis":"المحكمة الدستورية في مصر تقضي باحترام أحكام القضاء بشأن تيران وصنافير","label":"disagree"}
{"uid":255,"premise":"وقف المسلسل الأمريكي الكوميديروزان إثر تغريدة عنصرية عن مساعدة أوباما","hypothesis":"المسلسل الأمريكي الكوميديروزان يستمر رغم تغريدة عن مساعدة أوباما","label":"disagree"}
{"uid":1241,"premise":"الليرة التركية تواصل السقوط","hypothesis":"تواصل انخفاض الليرة التركية","label":"agree"}
{"uid":644,"premise":"دوائر لنظر قضايا الفساد لأول مرة في السعودية","hypothesis":"قضايا الفساد في السعودية دون دوائر لنظرها","label":"disagree"}
{"uid":400,"premise":"السعودية: اسقاط طائرة لاسلكية ترفيهية صغيرة بمنطقة القصور الملكية","hypothesis":"فشل الأمن السعودي فى اسقاط طائرة لاسلكية صغيرة مرت بالقرب من القصور الملكية","label":"disagree"}
{"uid":1145,"premise":"أول أيام الآلية الجديدة في السودان تشهد هبوطاً حاداً للجنيه","hypothesis":"أول أيام الآلية الجديدة في السودان تشهد ارتفاعاً كبيراً للجنيه","label":"disagree"}
{"uid":121,"premise":"السعودية لا تزال تعتقل 9 بينهم 4 سيدات بتهمة الإضرار بالأمن","hypothesis":"اعتقال 9 بينهم 4 سيدات بتهمة الإضرار بالأمن فى السعودية","label":"agree"}
{"uid":1389,"premise":"إيقاف عملية البحث عن مغن ألماني فقد قبالة الشواطئ الكندية","hypothesis":"التوقف عن البحث عن المغني الألماني الذي فُقد قرابة الشواطئ الكندية","label":"agree"}
{"uid":523,"premise":"محكمة عراقية تقضي بإعدام 16 امرأة تركية بتهمة الانضمام لتنظيم الدولة الإسلامية","hypothesis":"حكم ببراءة 16امرأة تركية","label":"disagree"}
{"uid":2101,"premise":"مقصية رونالدو تهوي بأسهم يوفنتوس","hypothesis":"التمسك برونالدو يصعد بأسهم اليوفي","label":"disagree"}
{"uid":81,"premise":"أردوغان يرد على ترامب بفرض عقوبات على وزيرين أمريكيين","hypothesis":"أردوغان يرفض معاقبة وزيرين أمريكيين بعد تصريحات ترامب","label":"disagree"}
{"uid":1206,"premise":"انخفاض جديد لليرة قبل اجتماع تركيا مع أمريكا","hypothesis":"انخفاض جديد لليرة قبل اجتماع تركيا مع روسيا","label":"disagree"}
{"uid":2123,"premise":"المتحدث باسم رئيس الوزراء الإسرائيلي يؤكد نقل نتنياهو للمستشفى","hypothesis":"المتحدث باسم رئيس الوزراء الأمريكي يؤكد نقل ترامب للمستشفى","label":"disagree"}
{"uid":604,"premise":"الذهب يتعافى وسط محادثات مزمعة بين أميركا والصين","hypothesis":"الذهب يتراجع جراء محادثات مزعمة بين الصين وأوروبا","label":"disagree"}
{"uid":2025,"premise":"الدولار يرتفع معوضا خسائر التعاملات المبكرة","hypothesis":"ارتفاع لسعر الدولار يعوض خسائر التعاملات المبكرة","label":"agree"}
{"uid":1488,"premise":"الليرة التركية تخسر الكثير أمام الدولار","hypothesis":"الليرة التركية تواصل الصعود أمام الدولار","label":"disagree"}
{"uid":1336,"premise":"محكمة سعودية ترفض زواج امرأة من رجل لأنه يعزف العود","hypothesis":"محكمة سعودية تقبل زواج امرأة من رجل رغم عزفه للعود","label":"disagree"}
{"uid":1169,"premise":"خسائر الطيران الروسي في سوريا منذ 2015","hypothesis":"تعرف على خسائر الطيران الروسي في سوريا منذ 2015","label":"agree"}
{"uid":2304,"premise":"مصر: إحالة هشام جنينة رئيس الجهاز المركزي للمحاسبات السابق للمحاكمة العسكرية","hypothesis":"مصر: هشام جنينة رئيس الجهاز المركزي للمحاسبات السابق يواحه المحاكمة العسكرية","label":"agree"}
{"uid":629,"premise":"ولي العهد السعودي: الإسرائيليون لهم حق في الأرض","hypothesis":"صرح ولي العهد السعودي بأن الإسرائيليين لهم حق في الأرض","label":"agree"}
{"uid":581,"premise":"واشنطن تغلق قنصليتها بالبصرة وتحمل طهران مسؤولية سلامة رعاياها","hypothesis":"فرنسا تغلق قنصليتها بالبصرة وتحمل طهران مسؤولية سلامة رعاياها","label":"disagree"}
{"uid":1717,"premise":"تراجع فادح للريال الإيراني.. وطوابير أمام مكاتب الصرافة","hypothesis":"أزمة لمحال الصرافة يسببها تراجع الريال","label":"agree"}
{"uid":88,"premise":"انتخاب أول امرأة لتولي منصب شيخ مدينة تونس","hypothesis":"امرأة فى تونس تفشل فى الحصول على منصب شيخ مدينة","label":"disagree"}
{"uid":789,"premise":"العملة الأرجنتينية تنهار و البنك المركز يتدخل","hypothesis":"العملة الأرجنتينية تنهار و الولايت المتحدة تتدخل","label":"disagree"}
{"uid":2497,"premise":"بريطانيا تطرح ورقة نقدية جديدة أكثر أمنا","hypothesis":"ورقة نقدية بريطانية جديدة","label":"agree"}
{"uid":218,"premise":"هل لمصر دور فاعل في المصالحة الفلسطينية؟","hypothesis":"هل للسعودية دور فاعل في المصالحة الفلسطينية؟","label":"disagree"}
{"uid":14,"premise":"أمريكا وتركيا: اتفاق بومبيو وأوغلو على الحوار والتعاون الوثيق لحل الخلافات","hypothesis":"خلاف بين بومبيو وأوغلو","label":"disagree"}
{"uid":1000,"premise":"إيران: مقتل 5 من أفراد الشرطة في اشتباكات مع صوفيين","hypothesis":"إيران: مقتل شخصين في اشتباكات عناصر الشرطة مع الصوفيين","label":"disagree"}
{"uid":807,"premise":"صفعة اقتصادية قوية لإيران","hypothesis":"إيران تتلقى صفعة اقتصادية قوية","label":"agree"}
{"uid":1898,"premise":"انهيار كبير للريال الإيراني","hypothesis":"انهيار كبير للريال السعودي","label":"disagree"}
{"uid":2504,"premise":"اكتشاف مومياء في تابوت فرعوني كان يُعتقد أنه فارغ طوال 150 عاما","hypothesis":"مومياء تكتشف في تابوت فرعوني كان يظن العلماء أنه فارغ طيلة الـ 150 عام الماضية","label":"agree"}
{"uid":568,"premise":"ما هي الأسئلة التي تدور بأذهانكم عن البوليساريو وملف الصحراء الغربية؟","hypothesis":"من هي العارضة البلجيكية التي أثارت الغضب بصورها العارية في مصر وإسرائيل؟","label":"other"}
{"uid":2413,"premise":"الذهب يهبط بعد تلميحات برفع الفائدة","hypothesis":"التلميحات برفع الفائدة يصعد بالذهب","label":"disagree"}
{"uid":1624,"premise":"نصف لوحات متحف فرنسي مزورة","hypothesis":"ألف ليلة وليلة حكايات ترويها لوحات نادرة لأسرة محمد علي","label":"other"}
{"uid":1470,"premise":"غموض بشأن مصير الإعلامي السعودي جمال خاشقجي","hypothesis":"تم الإعلان عن العثور على جمال خاشقجي","label":"disagree"}
{"uid":1499,"premise":"هل تجاهل أردوغان حقا أزمة بلاده الاقتصادية؟","hypothesis":"أردوغان يعترف بالأزمة الاقتصادية لبلده","label":"disagree"}
{"uid":787,"premise":"إنشاء وزارة الثقافة بالسعودية لتأمين المزيد من الرفاهية للشباب","hypothesis":"نفي السعودية ما يتردد عن إنشاء وزارات جديدة","label":"disagree"}
{"uid":639,"premise":"مؤسسة عالمية تحذر من تبعات كارثية لهبوط الليرة التركية","hypothesis":"مؤسسة عالمية تحذر من تداعيات كارثية لانهيار الدولار","label":"disagree"}
{"uid":2510,"premise":"إضراب في الجزائر مما أدى لتوقف بعض القطاعات","hypothesis":"إضراب في الجزائر مما أدى لمقتل اشخاص واصابة آخرين","label":"disagree"}
{"uid":947,"premise":"رفع إنتاج غاز الحقل الإيراني القطري المشترك لضعفين","hypothesis":"خفض أنتاج الغاز في الحقل الإيراني القطري","label":"disagree"}
{"uid":2346,"premise":"حريق يطال مخازن صناديق الانتخابية لجانب الرصافة من العاصمة العراقية","hypothesis":"الصناديق الانتخابية بأمان بعد حريق العاصمة العراقية","label":"disagree"}
{"uid":1004,"premise":"اختفاء جمال خاشقجي: تزايد الضغوط على السعودية مع زيارة وزير الخارجية الأمريكي للمملكة","hypothesis":"هدوء فى الجانب السعودى بشأن مصير جمال خاشقي","label":"disagree"}
{"uid":309,"premise":"نجمات بالسينما الهندية يروين تجاربهن مع التحرش الجنسي","hypothesis":"نجمات بالسينما الفرنسية يروين تجاربهن مع التحرش الجنسي","label":"disagree"}
{"uid":2127,"premise":"الذهب يتعافى واليورو يعاني بسبب الليرة التركية","hypothesis":"اليورو يعاني بسبب الليرة والذهب يرتفع","label":"agree"}
{"uid":1503,"premise":"مسيرات غزة: مقتل المسعفة الفلسطينية الشابة رزان النجار جريمة اغتيال إسرائيلية مكتملة الأركان","hypothesis":"ندّدت غزة بجريمة قتل الشابة رزان النجار على يد إسرائيل","label":"agree"}
{"uid":363,"premise":"انحدار قياسي جديد لليرة التركية","hypothesis":"الليرة التركية تنحدر مجدداً","label":"agree"}
{"uid":1528,"premise":"رغم القرض العملاق.. العملة الأرجنتينية تواصل الانزلاق","hypothesis":"العملة الأرجنتينية ترتفع بفعل قرض عملاق","label":"disagree"}
{"uid":1630,"premise":"زلزال الليرة يصل قبرص التركية.. واقتصاد أنقرة بمهب الريح","hypothesis":"تركيا تنتعش رغم تراجع الليرة","label":"disagree"}
{"uid":2202,"premise":"اختراع عالي المخاطرة يحطم أسعار تذاكر الطيران","hypothesis":"اختراع عالي المخاطرة يحطم أسعار تذاكر المباريات","label":"disagree"}
{"uid":1227,"premise":"النفط ينهي الأسبوع على خسائر مع انحسار القلق بشأن الإمدادات","hypothesis":"الإمدادات تنحسر والنفط ينهي أسبوعه على خسائر","label":"agree"}
{"uid":2603,"premise":"استهداف مطار في طرابلس بهجوم صاورخى و اجبار ليبيا على تغيير مسار الرحلات الجوية","hypothesis":"هدوء الاشتباكات فى طرابلس","label":"disagree"}
{"uid":2359,"premise":"السياحة الصينية في الإمارات تحقق أرقاماً قياسية","hypothesis":"السياحة الصينية في الإمارات تحقق نمواً ضئيلاً","label":"disagree"}
{"uid":1125,"premise":"اختفاء جمال خاشقجي: محمد بن سلمان ينفي لترامب معرفته بمصير الصحفي السعودي","hypothesis":"نفى محمد بن سلمان لترامب معرفته بمصير الصحفى جمال خاشقجي","label":"agree"}
{"uid":2414,"premise":"اتهام زوجة بنيامين نتنياهو بـالاحتيال وإساءة استخدام المال العام","hypothesis":"زوجة نتنياهو متهم بالاحتيال وإهدار المال العام","label":"agree"}
{"uid":2491,"premise":"إيفانكا ترامب وزوجها يحضران حفل افتتاح السفارة الأمريكية في القدس","hypothesis":"ترامب و زوجته من بين حضور حفل افتتاح السفارة الأمريكية في القدس","label":"agree"}
{"uid":162,"premise":"الصين تستنجد باوروبا لوقف سياسات ترامب","hypothesis":"مساع صينية  لردع خطط أوروبية بمساعدة ترامب","label":"disagree"}
{"uid":172,"premise":"29 قتيلا في هجوم بقذيفة صاروخية على سوق مزدحم شرقي دمشق","hypothesis":"سقوط 29 قتيلا فى سوق مزدحم بدمشق بعد هجوم بقذيفة صاورخية","label":"agree"}
{"uid":720,"premise":"برنت يغلق مستقرا والخام الأميركي يرتفع","hypothesis":"انخفاض برنت عند الاغلاق و ارتفاع للخام الأمريكي","label":"disagree"}
{"uid":780,"premise":"مظاهرات البصرة: توقف العمل في ميناء أم قصر عقب اشتباكات عنيفة","hypothesis":"توقف العمل فى ميناء أم قصر نتيجة للاشتباكات العنيفة فى مظاهرات البصرة","label":"agree"}
{"uid":2272,"premise":"كيف أصبحت بشرة نفرتيتي بيضاء؟","hypothesis":"كيف أصبحت بشرة نفرتيتي حمراء؟","label":"disagree"}
{"uid":149,"premise":"خطوات لإنقاذ الليرة التركية","hypothesis":"المركزي التركي يساهم في مشكلة انخفاض قيمة الليرة","label":"agree"}
{"uid":1997,"premise":"مصدر والوكالة الكورية للطاقة توقعان مذكرة تفاهم","hypothesis":"توقيع مذكرة تفاهم إماراتية كورية في مجال الطاقة","label":"agree"}
{"uid":540,"premise":"أوبك تقترب من المستوى المستهدف لخفض المخزونات","hypothesis":"رفع مخزونات أوبك للمستوى المطلوب","label":"disagree"}
{"uid":1143,"premise":"الحرب التجارية الأميركية الصينية تستعر","hypothesis":"واشنطن- بكين رحى الحرب التجارية تشتعل","label":"agree"}
{"uid":370,"premise":"هل نجحت عقوبات ترامب في هز بازار طهران؟","hypothesis":"ترامب يلغي عقوبات هز بازار طهران","label":"disagree"}
{"uid":1413,"premise":"السلطات الماليزية تجري تشريحا على جثمان البطش","hypothesis":"جثمان البطش يتعرض للتشريح من قبل السلطات الماليزية","label":"agree"}
{"uid":850,"premise":"ماذا بعد الحرب الكلامية المشتعلة بين واشنطن وطهران؟","hypothesis":"هدوء الموقف بين واشنطن و طهران","label":"disagree"}
{"uid":1283,"premise":"الرئيس الإيراني ينتقد عنف شرطة الأخلاق","hypothesis":"أنتقد الرئيس الإيراني العنف من شرطة الأخلاق","label":"agree"}
{"uid":1507,"premise":"تقوم الحكومة السورية بمحاصرة الغوطة الشرقية","hypothesis":"أعلنت الحكومة السورية عن توقف الهجوم على الغوطة الشرقية","label":"disagree"}
{"uid":1260,"premise":"بيل كوسبي دفع 3.4 مليون دولار لتسوية اتهام بالتحرش الجنسي","hypothesis":"بيل كوسبي يدفع مبلغ 3.4 مليون دولار ليحل أزمة اتهامه بالتحرش الجنسي","label":"agree"}
{"uid":2547,"premise":"الليرة التركية تهوي إلى مستويات جديدة","hypothesis":"هبوط لليرة التركية لمستوى جديد","label":"agree"}
{"uid":2474,"premise":"التغييرات في السعودية منذ أصبح محمد بن سلمان وليا للعهد","hypothesis":"لا تغييرات في السعودية منذ تولى محمد بن سلمان منصب ولي للعهد","label":"disagree"}
{"uid":2263,"premise":"النفط يرتفع وسط عراقيل في إمدادات فنزويلا","hypothesis":"النفط يرتفع وسط عراقيل في إمدادات السعودية","label":"disagree"}
{"uid":1661,"premise":"اللبنانيون المغتربون يشاركون فى الانتخابات لأول مرة","hypothesis":"المغتربون لا يستطيعون المشاركة فى الانتخابات اللبنانية","label":"disagree"}
{"uid":2301,"premise":"مظاهرات روسية تطالب بزيادة المعاش وليس سن المعاش","hypothesis":"مظاهرات روسية تطالب بالحرية","label":"disagree"}
{"uid":2240,"premise":"إيقاف أوبر بقرار من أردوغان","hypothesis":"إيقاف أمازون بقرار من أردوغان","label":"disagree"}
{"uid":2299,"premise":"الأردن:تراجع عقاري والعراقيون الأكثر إقبالا","hypothesis":"إقبال متزايد من قبل الأردنيين على شراء العقارات","label":"disagree"}
{"uid":2157,"premise":"الصين تبحث عن حلفاء في حربها التجارية مع أميركا","hypothesis":"اصطفاف دولي لجانب الصين في حربها التجارية مع أميركا","label":"disagree"}
{"uid":160,"premise":"هيومن رايتس ووتش تدعو دبي للكشف عن مصير ابنة حاكم الإمارة","hypothesis":"دعت هيومن رايتس ووتش دبي أن تقوم باعلان مصير ابنة حاكم الإمارة","label":"agree"}
{"uid":310,"premise":"بسبب مواقف ترامب.. مجموعة السبع في خطر","hypothesis":"مجموعة السبع القوية في خطر","label":"agree"}
{"uid":1093,"premise":"وزير المالية المصري: زيادة مرتقبة في الأجور والمعاشات","hypothesis":"خفض للمعاشات والأجور المصرية قريباً","label":"disagree"}
{"uid":68,"premise":"تقارير عن مقتل وإصابة إسرائيليين على يد مسلح فلسطيني","hypothesis":"أنباء عن مقتل أمريكيين على يد مسلح فلسطيني","label":"disagree"}
{"uid":2283,"premise":"شركة صينية غامضة تقلق العالم.. وترعب أميركا","hypothesis":"رعب صيني جراء شركة أميركية مجهولة","label":"disagree"}
{"uid":1965,"premise":"كندا تنتقم من ترامب","hypothesis":"انتقام كندي من رئيس الولايات المتحدة","label":"agree"}
{"uid":2334,"premise":"وفاة ميني مي عن عمر يناهز 49 عام","hypothesis":"وفاة ميني مي عن عمر يناهز 80 عام","label":"disagree"}
{"uid":1691,"premise":"كوريا الجنوبية ترسل سفينة لمكافحة قرصنة إلى ليبيا لإنقاذ مهندس مخطوف","hypothesis":"سفينة لمكافحة قرصنة من كوريا الجنوبية تبحر إلى ليبيا لإنقاذ مهندس مخطوف","label":"agree"}
{"uid":139,"premise":"تشريح جثتي سائحي الغردقة بعد أوامر من النيابة المصرية","hypothesis":"النيابة المصرية تأمر بتسليم جثتي سائحي الغردقة البريطانيين","label":"disagree"}
{"uid":2022,"premise":"الرئيس الإيراني ينتقد عنف شرطة الأخلاق","hypothesis":"شجع الرئيس الإيراني شرطة الأخلاق على العنف","label":"disagree"}
{"uid":1917,"premise":"تعهد أردوغان بإعلان نتائج التحقيق في قضية اختفاء جمال خاشقجي","hypothesis":"أردوغان غير مكترث بإعلان نتائج التحقيق في قضية اختفاء خاشقجي","label":"disagree"}
{"uid":509,"premise":"حريق تسبب في سقوط الطائرة المصرية فوق المتوسط في 2016","hypothesis":"سقوط الطائرة المصرية فوق البحر المتوسط فى 2016 كان بسبب حريق","label":"agree"}
{"uid":1372,"premise":"نشطاء: أكثر من نصف مليون قتيل في سوريا منذ اندلاع الحرب","hypothesis":"الحرب السورية تخلف دمار دون وقوع قتلى","label":"disagree"}
{"uid":716,"premise":"الذهب يتراجع من أعلى مستوى في 5 أسابيع","hypothesis":"تراجع لأسعار الذهب من أعلى مستوى في خمسة أسابيع","label":"agree"}
{"uid":1534,"premise":"ارتفاع قياسي في إيرادات قناة السويس السنوية","hypothesis":"إيرادات قناة السويس السنوية ترتفع ارتفاعاً قياسياً","label":"agree"}
{"uid":304,"premise":"تحقيق قناة السويس لأكبر عائدات لها في التاريخ","hypothesis":"تحقيق قناة السويس لأقل عائدات لها في التاريخ","label":"disagree"}
{"uid":1314,"premise":"انقلاب قطار بمنطقة بوقنادل و سقوط 7 قتلى على الأقل فى المغرب","hypothesis":"انقلاب قطار في المغرب دون وقع اصابات","label":"disagree"}
{"uid":2028,"premise":"تظاهر الآلاف في المغرب تنديدا بسجن قادة الحراك الشعبي","hypothesis":"الآلاف في المغرب يدعمون سجن قادة الحراك الشعبي","label":"disagree"}
{"uid":256,"premise":"تركيا ستتدخل بسوق العملات","hypothesis":"تركيا تتحفز التدخل في سوق العملات","label":"agree"}
{"uid":154,"premise":"تعلن الحكومة اللبنانية عن رفضها لرجوع اللاجئيين السوريين","hypothesis":"أعلنت الحكومة اللبنانية عن تأييدها التام قانونا لرجوع اللاجئيين السوريين","label":"disagree"}
{"uid":916,"premise":"السيسي يُصادق على قانون تشديد الرقابة على الإنترنت","hypothesis":"السيسي يرفض مشروع قانون تشديد الرقابة على الإنترنت","label":"disagree"}
{"uid":1455,"premise":"جلد رجل إيراني 80 جلدة لشربه الخمر حين كان طفلا","hypothesis":"الحكم بالجلد على رجل إيراني شرب الخمر في صغره","label":"agree"}
{"uid":2439,"premise":"أتهم روحانى واشنطن بالسعى لتغيير نظام الحكم الإيرانى","hypothesis":"روحانى يدعم تغيير نظام الحكم الإيرانى","label":"disagree"}
{"uid":1623,"premise":"العبادي يوقف وزير الكهرباء عن العمل بعد احتجاجات على الخدمات السيئة","hypothesis":"استمرار وزير الكهرباء فى منصبه رغم الاحتجاجات","label":"disagree"}
{"uid":228,"premise":"احتجاز صحفييْن مصرييْن 15 يوما بتهمة تكدير الأمن العام","hypothesis":"بسبب تكدير الأمن العام مصر تحتجز صحفييْن لمدة 15 يوم","label":"agree"}
{"uid":2442,"premise":"السعودية: تغييرات واسعة تشمل قيادات كبرى بالجيش في إطار رؤية تطوير استراتيجية","hypothesis":"تغييرات واسعة فى قيادات كبرى بالجيش فى السعودية","label":"agree"}
{"uid":1429,"premise":"نزيف الليرة التركية مستمر بعد العقوبات الأميركية","hypothesis":"الليرة التركية تواصل الهبوط جراء العقوبات الأميركية","label":"agree"}
{"uid":537,"premise":"مصر: اتفاق بمليار دولار لتوفير سلع أساسية للمواطنين","hypothesis":"سلع بمليار دولار للمواطنين اللبنانيين","label":"disagree"}
{"uid":1607,"premise":"الذهب عند أعلى مستوى بفعل الأزمة مع روسيا","hypothesis":"الأزمة مع تركيا تتسبب في ارتفاع الذهب لأعلى مستوى","label":"disagree"}
{"uid":177,"premise":"الحرب في سوريا: كيف يمكن أن تغير إدلب استراتيجية ترامب؟","hypothesis":"هل يمكن ان تتغير استراتيجية ترامب فى سوريا بسبب إدلب؟","label":"agree"}
{"uid":612,"premise":"إسبانيا تفك الشفرة السرية لرسائل عمرها 500 عام كتبها الملك فرديناند","hypothesis":"رسائل عمرها 1000عام كتبها الملك فرديناند تُفك  شفرتها من قبل إسبانيا","label":"disagree"}
{"uid":2403,"premise":"الصدر يطلب من العراقيين الاتحاد وعدم الدعوة لإعادة الانتخابات","hypothesis":"تأجيل التصويت على انتخاب رئيس العراق وسط تنافس غير مسبوق","label":"other"}
{"uid":1985,"premise":"مصر تعلن عن إجراءات حماية اجتماعية هذا العام","hypothesis":"أوسكار 2018: ما المتوقع خلال حفل توزيع الجوائز هذا العام","label":"other"}
{"uid":1906,"premise":"نساء غوطة دمشق يشاركن العالم قصصهن عبر فيسبوك","hypothesis":"نساء غوطة يشاركن حكايتهن للعالم عبر وسائل التواصل الاجتماعى","label":"agree"}
{"uid":43,"premise":"مصر.. رسوم جمركية جديدة للتشجيع والاستغناء","hypothesis":"رسوم جمركية مصرية على سلع لتشجيع المحلي","label":"agree"}
{"uid":64,"premise":"تصريحات ترامب تعوض خسائر النفط الأخيرة","hypothesis":"إعلان ترامب يلحق خسائر بالغة بأسعار النفط","label":"disagree"}
{"uid":536,"premise":"دعوة للعمل 4 أيام بالأسبوع فقط.. مع راتب أعلى","hypothesis":"دعوة لخفض الرواتب وزيادة أيام العمل","label":"disagree"}
{"uid":510,"premise":"أعلن الكنيست الإسرائيلي عن قراءة أولى لمشروع قانون يهودية الدولة المثير للجدل","hypothesis":"الكنيست الإسرائيلي يرفض مشروع قانون يهودية الدولة المثير للجدل","label":"disagree"}
{"uid":107,"premise":"فلسطين.. تعديلات ضريبية لزيادة الإيرادات","hypothesis":"تعديلات ضريبية فلسطينية لتحسين الإيرادات","label":"agree"}
{"uid":562,"premise":"روحاني يتعهد بمواجهة المسؤولين الأمريكيين المعادين لإيران","hypothesis":"روحاني يتوصل لاتفاق مع المسؤولين الأمريكيين","label":"disagree"}
{"uid":709,"premise":"100 ألف برميل يخسرهم الإنتاج الليبي يوميا بعد هجوم إرهابي","hypothesis":"20 ألف برميل يخسرهم الإنتاج الليبي يوميا بعد هجوم إرهابي","label":"disagree"}
{"uid":378,"premise":"النفط يرتفع مع هبوط مؤشر الدولار إلى أدنى مستوى","hypothesis":"هبوط حاد في أسعار النفط مع ارتفاع الدولار","label":"disagree"}
{"uid":1685,"premise":"اللبنانيون المغتربون يدلون بأصواتهم لأول مرة في الانتخابات","hypothesis":"اللبنانيون المغتربون يشاركون فى الانتخابات لأول مرة","label":"agree"}
{"uid":2518,"premise":"ريال إيران يسجل تدهورا قياسيا.. والعقوبات تزيد الطين بلة","hypothesis":"الريال الإيراني يتعافى رغم العقوبات","label":"disagree"}
{"uid":1770,"premise":"إقبال كثيف على التصويت في اليوم الأول لانتخابات الرئاسية المصرية","hypothesis":"إقبال ضعيف للغاية على لجان التصويت فى انتخابات الرئاسة المصرية","label":"disagree"}
{"uid":1660,"premise":"تنديد فلسطيني بالإفراج عن جندي إسرائيلي قتل جريحا","hypothesis":"تنديد فلسطيني واسع بعد الإفراج عن جندي إسرائيلي قتل جريحا","label":"agree"}
{"uid":469,"premise":"بعد الانهيار.. الليرة التركية تسجل ارتفاعا طفيفا","hypothesis":"ارتفاع طفيف لليرة التركية","label":"agree"}
{"uid":1158,"premise":"الأمم المتحدة تطالب مصر بإلغاء أحكام الاعدام الصادرة في قضية فض رابعة","hypothesis":"روسيا تطالب مصر بإلغاء أحكام الاعدام الصادرة في قضية فض رابعة","label":"disagree"}
{"uid":2448,"premise":"الريال والعقوبات.. سيناريو انهيار النظام الإيراني في 2019","hypothesis":"العقوبات والريال وسيلتان لنهضة إيران","label":"disagree"}
{"uid":896,"premise":"أردوغان غاضب ومحبط.. ويش هجوما تخوينيا","hypothesis":"الرئيس التركي متفائل بالوضع السياسي","label":"disagree"}
{"uid":1837,"premise":"تركيا: أمهات السبت لم يفقدن الأمل لمعرفة مصير أبنائهن المجهول منذ 23 عاماً","hypothesis":"أمهات السبت لم يفقدن الأمل لمعرفة المصير المجهول لابنائهن رغم مرور 23 عاماً","label":"agree"}
{"uid":1973,"premise":"النفط ينخفض وسط مخاوف من حرب تجارية","hypothesis":"مخاوف من حرب تجارية تؤدي إلى انخفاض سعر النفط","label":"agree"}
{"uid":645,"premise":"أوبك تقلص توقعاتها لنمو الطلب العالمي","hypothesis":"اوبك ترفع توقعاتها بشأن نمو الطلب العالمي","label":"disagree"}
{"uid":1358,"premise":"النفط يسجل أعلى مستوى بفضل تعافي أسواق الأسهم","hypothesis":"تدهور أسعار النفط بتراجع أسواق الأسهم","label":"disagree"}
{"uid":1261,"premise":"علم قطر على شعار مناورات درع الخليج 1 في السعودية","hypothesis":"وضع العلم القطرى على شعار مناورات درع الخليج 1 المقامة في السعودية","label":"agree"}
{"uid":1506,"premise":"4 دول عربية بين الـ6 الأغنى في أفريقيا","hypothesis":"قائمة الأغنى إفريقيا تخلو من الدول العربية","label":"disagree"}
{"uid":879,"premise":"صراع ما بعد الانتخابات في كردستان العراق","hypothesis":"تصالح ما بعد الانتخابات في كردستان العراق","label":"disagree"}
{"uid":1079,"premise":"نجوم هوليوود ينتقدون جائزة أوسكار الجديدة لـأفضل فيلم جماهيري","hypothesis":"جائزة أوسكار الجديدة لأفضل فيلم جماهيري تنقتد من قبل نجوم هوليوود","label":"agree"}
{"uid":2286,"premise":"الذهب يتراجع منهيا الأسبوع على مكاسب","hypothesis":"إنهاء أسبوع التداول بانخفاض رغم ارتفاع أسعار الذهب","label":"disagree"}
{"uid":2615,"premise":"الرئيس التركي يلوح بضرب شمال العراق ما لم تطهره بغداد من المسلحين الأكراد","hypothesis":"رئيس تركيا يلمح بضرب شمال العراق ما لم يتم تطهير بغداد من المسلحين الأكراد","label":"agree"}
{"uid":311,"premise":"اختفاء جمال خاشقجي: تزايد الضغوط على السعودية مع زيارة وزير الخارجية الأمريكي للمملكة","hypothesis":"تزايد الضغوط على السعودية بعد اختفاء جمال خاشقي مع زيارة وزير الخارجية الأمريكي للمملكة","label":"agree"}
{"uid":231,"premise":"افتتاح أول دار عرض في السعودية منذ أكثر من 35 عاما بفيلم النمر الأسود","hypothesis":"فيلم النمر الأسود يفتتح دار عرض سينمائي لأول مرة منذ 35 عام","label":"agree"}
{"uid":2389,"premise":"جواد ظريف من دمشق: يجب تطهير محافظة إدلب من الإرهابيين","hypothesis":"جواد ظريف يتحدث عن وجوب تطهير دمشق من المتظاهرين","label":"disagree"}
{"uid":1056,"premise":"نساء غوطة يشاركن حكايتهن للعالم عبر وسائل التواصل الاجتماعى","hypothesis":"نساء الغوطة منقطعات تماما عن العالم","label":"disagree"}
{"uid":1981,"premise":"قضية فتاة التجمع: هل ستعاقب صاحبة فيديو القهوة المثير للجدل في مصر؟","hypothesis":"هل سيتم معاقبة فتاة فيديو القهوة المثير للجدل فى مصر ؟","label":"agree"}
{"uid":748,"premise":"وزارة الصحة: مقتل 3 فلسطينيين في مظاهرات غزة اليوم","hypothesis":"الجيش الأمريكي يعلن مقتل إرهابيين اثنين في غارة جوية جنوبي ليبيا","label":"other"}
{"uid":2107,"premise":"شخصية الدب ويني تثير جدلا في الصين","hypothesis":"شخصية بطوط تثير جدلا في الصين","label":"disagree"}
{"uid":670,"premise":"حادث الطائرة التركية: مصرع ابنة رجل أعمال وصديقاتها بعد حفل في الإمارات","hypothesis":"مصرع ابنة رجل أعمال وصديقاتها فى حادث الطائرة التركية بعد حضورهم لحفل في الإمارات","label":"agree"}
{"uid":758,"premise":"إطلاق تطبيق على الهاتف المحمول لتقييم الخطب الدينية فى السعودية","hypothesis":"رفض قاطع لتطبيق على الهاتف المحمول لتقييم الخطب الدينية فى السعودية","label":"disagree"}
{"uid":2130,"premise":"جمال خاشقجي: أمس ما يحتاجه العالم العربي هو حرية التعبير","hypothesis":"جمال خاشقجي: العالم العربي في حاجة ماسة لحرية التعبير","label":"agree"}
{"uid":1972,"premise":"محكمة مصرية تقضي بإعدام 3 أشخاص في قضية تنظيم كتائب أنصار الشريعة","hypothesis":"براءة 3 أشخاص في قضية تنظيم كتائب أنصار الشريعة","label":"disagree"}
{"uid":766,"premise":"محكمة العدل الدولية تبحث دعوى إيران لتعليق العقوبات الأمريكية","hypothesis":"محمكة العدل الدولية تناقش مطالب إيران بوقف العقوبات الأمريكية","label":"agree"}
{"uid":2031,"premise":"واشنطن تقرر سحب بعض أنظمة باتريوت من الكويت والبحرين والأردن","hypothesis":"واشنطن تقرر سحب بعض أنظمة باتريوت من مصر","label":"disagree"}
{"uid":2223,"premise":"المركزي التركي يخالف التوقعات.. والليرة تدفع الثمن","hypothesis":"ارتفاع على ثمن الليرة التركية بسبب إجراءات البنك المركزي","label":"agree"}
{"uid":541,"premise":"رقم قياسي جديد لقناة السويس","hypothesis":"السويس تعجز عن تحقيق أي رقم قياسي","label":"disagree"}
{"uid":1615,"premise":"مستشار أردوغان: جمال خاشقجي قتل في القنصلية السعودية","hypothesis":"مستشار أردوغان ينفي مقتل جمال خاشقجي في القنصلية السعودية","label":"disagree"}
{"uid":854,"premise":"نيكاي يرتفع لأعلى مستوى منذ 1991","hypothesis":"نيكاي ينخفض لأدنى مستوى منذ ١٩٩١","label":"disagree"}
{"uid":2095,"premise":"الرئيس السوداني يستبدل رئيس الأركان ضمن تغييرات في قيادات الجيش","hypothesis":"السودان: استبدال رئيس الأركان ضمن تغييرات في قيادات الجيش","label":"agree"}
{"uid":1137,"premise":"دار الأوبرا المصرية تحيي أول حفلاتها في السعودية","hypothesis":"لأول مرة حفل لفنانة مصرية في السعودية","label":"disagree"}
{"uid":2584,"premise":"بسبب مواقف ترامب.. مجموعة السبع في خطر","hypothesis":"مواقف ترامب تدعم الدول الصناعية السبع","label":"disagree"}
{"uid":197,"premise":"الأسهم الأميركية تهبط بالدولار","hypothesis":"الأسهم الأميركية ترتفع بالدولار","label":"disagree"}
{"uid":768,"premise":"محكمة عسكرية مصرية تقضي بحبس هشام جنينة خمس سنوات","hypothesis":"حكم بحبس هشام جنينة خمس سنوات","label":"agree"}
{"uid":409,"premise":"إسرائيل تتهم إيران بقصف الجولان بالصواريخ وإطلاق صفارات الإنذار","hypothesis":"إيران تقصف الجولان بالصواريخ و إسرائيل تطلق صفارات الإنذار","label":"agree"}
{"uid":1699,"premise":"جدلاً واسعاً بسبب القس الذي قاد صلاة افتتاح السفارة الأمريكية في القدس","hypothesis":"جدلاً واسعاً بسبب القس الذي قاد صلاة افتتاح السفارة الروسية في القدس","label":"disagree"}
{"uid":442,"premise":"الفيلم الكوميدي  موت ستالين  يُمنع من العرض في روسيا ","hypothesis":"فيلم الأكشن  موت ستالين  يُمنع من العرض في روسيا ","label":"disagree"}
{"uid":1834,"premise":"من الذين يشملهم قرار مصادرة أملاك رموز حكم صدام؟","hypothesis":"إلغاء مصادرة أملاك رموز حكم صدام حسين","label":"disagree"}
{"uid":1176,"premise":"العفو الدولية: تسليح السعودية وحلفائها ألحق أضرارا هائلة بالمدنيين في اليمن","hypothesis":"أعلنت منظمة العفو الدولية أن تسليح السعودية وحلفائها سبب اضرارا كبيرة للمدنيين في اليمن","label":"agree"}
{"uid":1806,"premise":"ما صلاحيات أردوغان في ظل النظام الرئاسي؟","hypothesis":"تقلص صلاحيات أردوغان في تركيا","label":"disagree"}
{"uid":840,"premise":"السعودية تمهل السفير الكندي 24 ساعة لمغادرة أراضيها","hypothesis":"مهلة 24 ساعة للسفير الكندي لمغادرة السعودية","label":"agree"}
{"uid":447,"premise":"إضراب يشل أهم موانئ إسرائيل","hypothesis":"تعرف على تفاصيل قانون يهودية دولة إسرائيل","label":"other"}
{"uid":72,"premise":"ترحيب بظهور أشهر عارضات الأزياء الممتلئات في العالم من دون رتوش","hypothesis":"هل دفعت قطر أكبر فدية في التأريخ لتحرير الأمراء المخطوفين في العراق؟","label":"other"}
{"uid":1031,"premise":"السمك المملح: هل كانت إسرائيل مستعدة للتضحية بصحفي كي تصل لعرفات؟","hypothesis":"السمك المملح: هل كانت روسيا مستعدة للتضحية بصحفي كي تصل لعرفات؟","label":"disagree"}
{"uid":1322,"premise":"شابة لبنانية تطلق مشروع رسم على إنستغرام بسبب أنف أختها","hypothesis":"فتاة لبنانية تطلق على إنستغرام مشروع رسم بسبب أنف أختها!","label":"agree"}
{"uid":1736,"premise":"فتح تحقيق في قضية موت مريم مصطفى في مدينة روما","hypothesis":"فتح تحقيق في قضية موت مريم مصطفى في مدينة باريس","label":"disagree"}
{"uid":547,"premise":"اتفاق لتنظيم العمالة بين الكويت والفلبين","hypothesis":"الكويت ترفض تنظيم العمالة الفلبينية","label":"disagree"}
{"uid":2610,"premise":"الدولار يسجل أعلى مستوى هذا العام","hypothesis":"أعلى مستوى لسعر الدولار هذ العام","label":"agree"}
{"uid":2011,"premise":"الصين تخفض رسوم استيراد السيارات الجمركية","hypothesis":"الصين ترفع رسوم الجمارك على السيارات","label":"disagree"}
{"uid":882,"premise":"أسعار الذهب تسجل أدنى مستوياتها في 6 أشهر","hypothesis":"تسجيل أعلى مستوى للذهب في ٦ أشهر","label":"disagree"}
{"uid":2498,"premise":"أردوغان: يجب أن تثبت السعودية أن جمال خاشقجي قام بمغادرة القنصلية في إسطنبول","hypothesis":"أردوغان يلا يتوقع قيام السعودية بقتل جمال خاشقجي","label":"disagree"}
{"uid":78,"premise":"منظمة حقوقية تعلن ان ليبيا غير جاهزة لإجراء انتخابات حرة ونزيهة","hypothesis":"منظمة حقوقية تدعو لإجراء انتخابات في ليبيا","label":"disagree"}
{"uid":2399,"premise":"تراجع التضخم السنوي في الجزائر","hypothesis":"التضخم يتراجع في الجزائر","label":"agree"}
{"uid":2136,"premise":"دي ميستورا مستعد للذهاب بنفسي إلى إدلب لضمان الخروج الآمن للمدنيين","hypothesis":"قال دي ميستورا أنه مستعد للذهاب بنفسهإلى إدلب حتى يضمن الخروج الآمن للمدنيين","label":"agree"}
{"uid":2366,"premise":"السعودية تفتتح أول دار عرض سينمائي منذ 40 عاما","hypothesis":"أول أوبرا في السعودية بعد أكثر من 40 عام","label":"disagree"}
{"uid":1529,"premise":"مصر تجري تقييما مرحليا للمشاريع السياحية قيد التنفيذ","hypothesis":"مصر تستثني مشاريع سياحية من التقييم","label":"disagree"}
{"uid":669,"premise":"الليرة التركية تحطم الأرقام.. انهيار مستمر وأردوغان لايتزحزح","hypothesis":"أردوغان يتمسك بقراراته والليرة تواصل التراجع","label":"agree"}
{"uid":1023,"premise":"النفط يرتفع مع إعلان استمرار قيود الإنتاج","hypothesis":"انخفاض سعر النفط بعد إعلان استمرار قيود الإنتاج","label":"disagree"}
{"uid":196,"premise":"إنتاج مصر من الغاز يحقق قفزة في أكتوبر","hypothesis":"قفزة لإنتاج ليبيا من الغاز في أكتوبر","label":"disagree"}
{"uid":2339,"premise":"الحرب التجارية الأميركية الصينية تستعر","hypothesis":"توقف الحرب التجارية بين الصين وترامب","label":"disagree"}
{"uid":855,"premise":"النفط يقفز لأعلى مستوياته في 6 أسابيع","hypothesis":"الأعلى في ٦ أسابيع: قفزة في أسعار النفط","label":"agree"}
{"uid":1142,"premise":"اختفاء خاشقجي: تركيا تنفي تسليم أي تسجيلات للولايات المتحدة","hypothesis":"تركيا تسلم تسجيلات هامة للولايات المتحدة فى قضية خاشقجي","label":"disagree"}
{"uid":1519,"premise":"أعلى مرجع شيعي يحض العراقيين على عدم انتخاب الفاشلين والفاسدين في الانتخابات النيابية","hypothesis":"مرجع شيعى يجيز انتخاب الفاشلين !","label":"disagree"}
{"uid":461,"premise":"أسواق السيارات الكهربائية قريبا تحت الغزو الصيني","hypothesis":"خطة يابانية لغزو سوق السيارات الكهربائية","label":"disagree"}
{"uid":931,"premise":"السعودية تعترض صاروخا باليستيا من اليمن استهدف نجران","hypothesis":"القوات السعودية: اعتراض صاروخ باليستيا من اليمن استهدف نجران","label":"agree"}
{"uid":2163,"premise":"الحرب التجارية الوشيكة بين أميركا والصين قد تشمل المكسرات والفاكهة","hypothesis":"المكسرات والفاكهة خارج نطاق الحرب التجارية المحتملة بين أميركا والصين","label":"disagree"}
{"uid":2252,"premise":"مصدر والوكالة الكورية للطاقة توقعان مذكرة تفاهم","hypothesis":"الوكالة الكورية للغاز توقع مذكرة تفاهم مع شركة إماراتية","label":"disagree"}
{"uid":1238,"premise":"جائزة مان بوكر المرموقة من نصيب البريطانية آنا بيرنز عن روايتها بائع الحليب","hypothesis":"جائزة مان بوكر المرموقة من نصيب الفرنسية آنا بيرنز عن روايتها بائع الحليب","label":"disagree"}
{"uid":1762,"premise":"الدفاع الجوي السعودي يعترض صاروخا فوق الرياض","hypothesis":"التصدي لصاروخ فوق الرياض من قبل الدفاع الجوي السعودي","label":"agree"}
{"uid":265,"premise":"مساع صينية لردع ترامب بـخطة أوروبية","hypothesis":"مساع صينية  لردع خطط أوروبية بمساعدة ترامب","label":"disagree"}
{"uid":2104,"premise":"ترامب يحذر روحاني من مغبة تهديد الولايات المتحدة","hypothesis":"حذر الرئيس الأمريكى ترامب روحاني من مغبة تهديد الولايات المتحدة","label":"agree"}
{"uid":911,"premise":"تتويج أول امرة سمراء البشرة بلقب ملكة جمال بريطانيا","hypothesis":"تتويج أول امرة بيضاء البشرة بلقب ملكة جمال بريطانيا","label":"disagree"}
{"uid":293,"premise":"ناشطة سعودية: حياتي كلها صارت على تويتر دفاعا عن النساء","hypothesis":"ناشطة سعودية: حياتي كلها صارت على تويتر دفاعا عن الرجال","label":"disagree"}
{"uid":2421,"premise":"فضيحة الديزل تكلّف فولكسفاجن مليار يورو","hypothesis":"مليار يورو تتكبدها فولكسفاجن","label":"agree"}
{"uid":2521,"premise":"إحباط هجوم انتحاري على كنيسة في القاهرة","hypothesis":"من القاهرة إلى طوكيو.. انفجار مستمر بأكبر مدن العالم","label":"other"}
{"uid":2017,"premise":"الممثلة الإباحية ستورمي دانيلز تغيب عن بيغ براذر في اللحظات الأخيرة لـخلاف مع المنتجين","hypothesis":"ستورمي دانيلز تغيب عن بيغ براذر في اللحظات الأخيرة لـخلافها مع المنتجين","label":"agree"}
{"uid":1109,"premise":"لقد أخرجت الجالية الأرمنية أول رئيس وزراء مصري","hypothesis":"لم يتولى أحد من الجالية الأرمنية في مصر أي منصب مهم","label":"disagree"}
{"uid":484,"premise":"الناخبون في مصر يتوجهون لصناديق الاقتراع في الانتخابات الرئاسية","hypothesis":"إقبال كبير على صناديق الإنتخابات الرئاسية في مصر","label":"agree"}
{"uid":1450,"premise":"رفع أسعار الفائدة يرفع الدولار لأعلى مستوى","hypothesis":"توقعات خفض أسعار الفائدة يهبط بالدولار","label":"disagree"}
{"uid":2489,"premise":"10 نجوم يشاركوا في السياسة آخرهم بطلة  الجنس و المدينة ","hypothesis":"10 نجوم يشاركوا في السياسة آخرهم مخرج الجنس و المدينة ","label":"disagree"}
{"uid":1130,"premise":"انخفاض الليرة التركية لمستوى قياسي جديد","hypothesis":"ارتفاع الليرة التركية لمستوى قياسي جديد","label":"disagree"}
{"uid":2557,"premise":"الذهب ينخفض مع فشل أزمة إيران في تحفيز المشتريات","hypothesis":"الذهب يتعافى من خسائره","label":"disagree"}
{"uid":2284,"premise":"الذهب ينخفض بفعل صعود الدولار وزيادة عوائد السندات","hypothesis":"عوائد السندات وصعود الدولار يهبطان بالذهب","label":"agree"}
{"uid":2297,"premise":"فورد تستدعي مليوني سيارة بسبب عيوب خطيرة","hypothesis":"بسبب عيوب خطيرة: إرجاع مليوني سيارة فورد","label":"agree"}
{"uid":157,"premise":"من هو نبيه بري الذي يرأس برلمان لبنان للمرة السادسة؟","hypothesis":"تساؤلات عن حقيقة شخصية نبيه بري","label":"agree"}
{"uid":351,"premise":"بدء التفتيش في دوما السورية من قبل منظمة حظر الأسلحة الكيمياوية","hypothesis":"مفتشو منظمة حظر الأسلحة الكيمياوية في الضفة الغربية","label":"disagree"}
{"uid":31,"premise":"تيلرسون في أنقرة التي تطالب باستبعاد ميليشيا كردية من قوات سوريا الديمقراطية","hypothesis":"حرصت تيلرسون على طرد ميليشيا كردية من القوات السورية","label":"agree"}
{"uid":983,"premise":"إيفانكا ترامب وزوجها يحضران حفل افتتاح السفارة الأمريكية في القدس","hypothesis":"ترامب و زوجته يغيبان عن حضور حفل افتتاح السفارة الأمريكية في القدس","label":"disagree"}
{"uid":958,"premise":"بعد وصول النفط لأعلى مستوى في 3 أسابيع .. أسعار النفط تستقر","hypothesis":"بعد وصول النفط لأعلى مستوى في 3 أسابيع .. أسعار النفط تزداد","label":"disagree"}
{"uid":570,"premise":"بوتن يسعى لإصلاحات اقتصادية في ولايته الرابعة","hypothesis":"رئيس روسيا في ولايته الرابعة يتفادى الإصلاحات الاقتصادية","label":"disagree"}
{"uid":1427,"premise":"مشروع عملاق في قناة السويس.. و50 ألف فرصة عمل","hypothesis":"مشروع جديد يوفر ٥٠ الف فرصة عمل في قناة السويس","label":"agree"}
{"uid":791,"premise":"حكم بإعدام 16امرأة تركية بتهمة الانضمام لتنظيم الدولة الإسلامية فى العراق","hypothesis":"حكم ببراءة 16امرأة تركية","label":"disagree"}
{"uid":1884,"premise":"تركيا.. التضخم يرتفع والليرة تتراجع لمستوى قياسي","hypothesis":"الليرة تتعافى في تركيا والتضخم يتراجع","label":"disagree"}
{"uid":1218,"premise":"ما غايات الأطراف المشاركة في معركة عفرين؟","hypothesis":"ما غايات الأطراف المشاركة في معركة الجولان؟","label":"disagree"}
{"uid":2013,"premise":"النفط يهبط من أعلى مستوياته","hypothesis":"هبوط قياسي للنفط من أعلى مستوى","label":"agree"}
{"uid":1303,"premise":"الانتخابات الرئاسية المبكرة في تركيا: المعارضة تختار محرم اينجه لمنافسة أردوغان","hypothesis":"تأييد المعارضة في تركيا لأردوغان في الإنتخابات الرئاسية","label":"disagree"}
{"uid":132,"premise":"مصر.. ارتفاع قياسي جديد للاحتياطي الأجنبي","hypothesis":"زيادة قياسية للاحتياطي الاجنبي في مصر","label":"agree"}
{"uid":1166,"premise":"اتهامات للقوات الحكومية السورية بـ استخدام غاز الكلور في الغوطة الشرقية","hypothesis":"اتهامات تطال القوات الحكومية فى سوريا باستخدام غاز الكلور في الغوطة الشرقية","label":"agree"}
{"uid":2333,"premise":"ريم بنا: رحيل فنانة فلسطينية جابت أغانيها الأرض","hypothesis":"مقتل الفنانة الفلسطينية ريم بنا","label":"disagree"}
{"uid":1559,"premise":"مقتل 257 في تحطم طائرة نقل عسكرية بالجزائر","hypothesis":"إرتفاع عدد ضحايا حادث الطائرة الجزائرية","label":"agree"}
{"uid":2206,"premise":"سحب الفيلم الصيني الأغلى تكلفة من دور العرض بسبب صعف إيراداته","hypothesis":"سحب الفيلم الصيني الأقل تكلفة من دور العرض بسبب صعف إيراداته","label":"disagree"}
{"uid":788,"premise":"بومبيو يتهم إيران باستغلال محكمة العدل الدولية لأغراض سياسية","hypothesis":"بومبيو يتهم العراق باستغلال محكمة العدل الدولية لأغراض سياسية","label":"disagree"}
{"uid":2221,"premise":"الخارجية الإيرانية: سنرد بإجراء مضاد إذا منعت الولايات المتحدة صادراتنا النفطية","hypothesis":"الخارجية الإيرانية تهدد بإجراءات مضادة إذا أوقفت الولايات المتحدة صادرات إيران النفطية","label":"agree"}
{"uid":2560,"premise":"النقد الدولي: نظرة إيجابية لنمو الاقتصاد المصري","hypothesis":"النقد الدولي يسخر من إمكانات الاقتصاد المصري","label":"disagree"}
{"uid":144,"premise":"قام الجيش المصري بقتل 16 عنصرا إرهابيا في سيناء","hypothesis":"أخفق الجيش المصري في الوصل إلى العناصر التكفيرية في سيناء","label":"disagree"}
{"uid":2186,"premise":"إعادة إعمار العراق يتطلب تكلفة تتخطى 88 مليار دولار","hypothesis":"إعادة إعمار العراق يلا يكلف الكثير","label":"disagree"}
{"uid":1193,"premise":"انخفاض أسعار النفط بعد زيادة إنتاج أوبك","hypothesis":"تراجع أسعار النفط بفعل قلة إنتاج أوبك","label":"disagree"}
{"uid":2260,"premise":"الليرة في تراجع قياسي وارتفاع للتضخم في تركيا","hypothesis":"الليرة تتعافى في تركيا والتضخم يتراجع","label":"disagree"}
{"uid":493,"premise":"الليرة التركية.. صعود طفيف بعد الانتخابات","hypothesis":"انخفاض ملحوظ لقيمة الليرة التركية","label":"disagree"}
{"uid":2443,"premise":"بعد اتهامه بسوء السلوك : مخرج فيلم قصة لعبة يرحل عن ديزني","hypothesis":"بعد اتهامه بالتحرش : مخرج فيلم قصة لعبة يرحل عن ديزني","label":"agree"}
{"uid":870,"premise":"إضراب عمالي يشل قطارات فرنسا","hypothesis":"العمال يشلون القطارات الفرنسية","label":"agree"}
